MANIFEST.in
README.md
requirements.txt
setup.py
metrics/__init__.py
metrics/config.py
metrics/context.py
metrics/decorators.py
metrics/exceptions.py
metrics/logger.py
metrics/backends/__init__.py
metrics/backends/base.py
metrics/backends/dd.py
mm_metrics.egg-info/PKG-INFO
mm_metrics.egg-info/SOURCES.txt
mm_metrics.egg-info/dependency_links.txt
mm_metrics.egg-info/requires.txt
mm_metrics.egg-info/top_level.txt