Metadata-Version: 1.1
Name: mm-metrics
Version: 0.5.2
Summary: Python client library abstracting away metrics collection
Home-page: https://github.com/Morgan-and-Morgan/metrics-python/
Author: Morgan & Morgan Developers
Author-email: developers@forthepeople.com
License: BSD License
Platform: UNKNOWN
Classifier: Environment :: Web Environment
Classifier: Intended Audience :: Developers
Classifier: License :: OSI Approved :: BSD License
Classifier: Operating System :: OS Independent
Classifier: Programming Language :: Python
Classifier: Programming Language :: Python :: 3
Classifier: Programming Language :: Python :: 3.4
Classifier: Programming Language :: Python :: 3.5
Classifier: Topic :: Internet :: WWW/HTTP
Classifier: Topic :: Internet :: WWW/HTTP :: Dynamic Content
